dtb_dev.py
dtb.dev-1.0.3.dist-info/WHEEL
dtb.dev-1.0.3.dist-info/METADATA
dtb.dev-1.0.3.dist-info/RECORD
