Metadata-Version: 2.1
Name: dtb.dev
Version: 1.0.3
Summary: DTB: Base dev tools
License: MIT
Author: Dima Doroshev
Author-email: dima@doroshev.com
Requires-Python: >=3.9,<4.0
Classifier: License :: OSI Approved :: MIT License
Classifier: Programming Language :: Python :: 3
Classifier: Programming Language :: Python :: 3.9
Provides-Extra: devtools
Requires-Dist: autoflake (>=1.4,<2.0); extra == "devtools"
Requires-Dist: black (>=20.8b1,<21.0)
Requires-Dist: flake8 (>=3.8.4,<4.0.0)
Requires-Dist: flake8-bandit (>=2.1.2,<3.0.0)
Requires-Dist: flake8-bugbear (>=20.1.4,<21.0.0)
Requires-Dist: flake8-builtins (>=1.5.3,<2.0.0)
Requires-Dist: flake8-comprehensions (>=3.2.3,<4.0.0)
Requires-Dist: flake8-debugger (>=3.2.1,<4.0.0)
Requires-Dist: flake8-eradicate (>=0.4.0,<0.5.0)
Requires-Dist: flake8-isort (>=4.0.0,<5.0.0)
Requires-Dist: flake8-print (>=3.1.4,<4.0.0)
Requires-Dist: flake8-quotes (>=3.2.0,<4.0.0)
Requires-Dist: flake8-string-format (>=0.3.0,<0.4.0)
Requires-Dist: isort (>=5.6.1,<6.0.0); extra == "devtools"
Requires-Dist: jedi (>=0.17.2,<0.18.0); extra == "devtools"
Requires-Dist: mccabe (>=0.6.1,<0.7.0)
Requires-Dist: mypy
Requires-Dist: pep8-naming (>=0.11.1,<0.12.0)
Requires-Dist: pre-commit (>=2.7.1,<3.0.0); extra == "devtools"
Requires-Dist: ptipython (>=1.0.1,<2.0.0); extra == "devtools"
Requires-Dist: pytest (>=6.1.1,<7.0.0)
Requires-Dist: pytest-cov (>=2.10.1,<3.0.0)
